scipy_dae-0.1.0.dist-info/METADATA
scipy_dae-0.1.0.dist-info/WHEEL
scipy_dae/__init__.py
scipy_dae/integrate/__init__.py
scipy_dae/integrate/_dae/__init__.py
scipy_dae/integrate/_dae/base.py
scipy_dae/integrate/_dae/bdf.py
scipy_dae/integrate/_dae/common.py
scipy_dae/integrate/_dae/dae.py
scipy_dae/integrate/_dae/radau.py
scipy_dae/integrate/_dae/tests/__init__.py
scipy_dae/integrate/_dae/tests/test_check_arguments.py
scipy_dae/integrate/_dae/tests/test_consistent_initial_conditions.py
scipy_dae/integrate/_dae/tests/test_integration_complex.py
scipy_dae/integrate/_dae/tests/test_integration_linear.py
scipy_dae/integrate/_dae/tests/test_integration_rational.py
scipy_dae/integrate/_dae/tests/test_integration_robertson.py
scipy_dae/integrate/_dae/tests/test_events.py
scipy_dae/integrate/_dae/benchmarks/__init__.py
scipy_dae/integrate/_dae/benchmarks/common.py
scipy_dae-0.1.0.dist-info/RECORD
