Metadata-Version: 2.1
Name: scipy_dae
Version: 0.1.0
Summary: Python implementation of solvers for differential algebraic equations (DAEs) and implicit differential equations (IDEs) that should be added to scipy one day.
Author-Email: Jonas Breuling <jonas.breuling@inm.uni-stuttgart.de>
Classifier: Development Status :: 4 - Beta
Classifier: Intended Audience :: Science/Research
Classifier: Intended Audience :: Developers
Classifier: License :: OSI Approved :: BSD License
Classifier: Programming Language :: Python
Classifier: Programming Language :: Python :: 3
Classifier: Programming Language :: Python :: 3.8
Classifier: Programming Language :: Python :: 3.9
Classifier: Programming Language :: Python :: 3.10
Classifier: Programming Language :: Python :: 3.11
Classifier: Programming Language :: Python :: 3.12
Classifier: Topic :: Software Development :: Libraries
Classifier: Topic :: Scientific/Engineering
Classifier: Operating System :: Microsoft :: Windows
Classifier: Operating System :: POSIX :: Linux
Classifier: Operating System :: POSIX
Classifier: Operating System :: Unix
Classifier: Operating System :: MacOS
Project-URL: homepage, https://github.com/JonasBreuling/scipy_dae
Project-URL: documentaton, https://github.com/JonasBreuling/scipy_dae
Project-URL: source, https://github.com/JonasBreuling/scipy_dae
Project-URL: download, https://github.com/JonasBreuling/scipy_dae/releases
Project-URL: tracker, https://github.com/JonasBreuling/scipy_dae/issues
Requires-Python: >=3.10
Requires-Dist: numpy>=2.0.1
Requires-Dist: scipy>=1.14.0
Requires-Dist: matplotlib>=3.4.3
Provides-Extra: dev
Requires-Dist: pytest; extra == "dev"
Requires-Dist: pytest-cov; extra == "dev"
